ganttlogger/__init__.py
ganttlogger/app.py
ganttlogger/config/font/ipaexg.ttf
ganttlogger/modules/Alone.py
ganttlogger/modules/CommonObservePackages.py
ganttlogger/modules/Displayer.py
ganttlogger/modules/Global.py
ganttlogger/modules/InitProcess.py
ganttlogger/modules/Logger.py
ganttlogger/modules/MacObservePackages.py
ganttlogger/modules/Merger.py
ganttlogger/modules/Observer.py
ganttlogger/modules/Plotter.py
ganttlogger/modules/Public.py
ganttlogger/modules/WinObservePackages.py
ganttlogger-0.2.2.dist-info/METADATA
ganttlogger-0.2.2.dist-info/WHEEL
ganttlogger-0.2.2.dist-info/entry_points.txt
ganttlogger-0.2.2.dist-info/top_level.txt
ganttlogger-0.2.2.dist-info/RECORD
