Metadata-Version: 2.1
Name: ganttlogger
Version: 0.2.2
Summary: This CLI will monitor(active-tab, mouse, keyboard), log, and plot graphs.
Home-page: https://github.com/KagenoMoheji/GanttLogger
Author: Goki Sugimura(KagenoMoheji)
Author-email: shadowmoheji.pd@gmail.com
License: MIT
Keywords: gantt,log,graph,plot,keyboard,mouse,active tab,monitor,ganttlogger
Platform: UNKNOWN
Classifier: Development Status :: 4 - Beta
Classifier: Natural Language :: English
Classifier: License :: OSI Approved :: MIT License
Classifier: Programming Language :: Python :: 3.7
Classifier: Operating System :: MacOS :: MacOS X
Classifier: Operating System :: Microsoft :: Windows
Requires-Dist: matplotlib
Requires-Dist: numpy
Requires-Dist: psutil
Requires-Dist: pynput
Requires-Dist: pypiwin32 ; platform_system == "Windows"
Requires-Dist: colorama ; platform_system == "Windows"
